ventrun/__init__.py
ventrun/__main__.py
ventrun/events.py
ventrun-1.8.dist-info/licenses/LICENSE
ventrun-1.8.dist-info/METADATA
ventrun-1.8.dist-info/WHEEL
ventrun-1.8.dist-info/entry_points.txt
ventrun-1.8.dist-info/top_level.txt
ventrun-1.8.dist-info/RECORD
