Metadata-Version: 2.4
Name: ventrun
Version: 1.8
Summary: Bootstrap your application and emit a Main event to ModuVent.
Author-email: Joxos <xujunhao61@163.com>
Requires-Python: >=3.13
License-File: LICENSE
Requires-Dist: loguru>=0.7.3
Requires-Dist: moduvent>=5.8
Dynamic: license-file
